engine/projects/1789815774207/rtl/alu.sv
module alu (
    input  logic [7:0] a,
    input  logic [7:0] b,
    input  logic [2:0] op,

    output logic [7:0] result,
    output logic       zero,
    output logic       carry
);

    logic [8:0] temp;

    always_comb begin
        result = 8'h00;
        carry  = 1'b0;
        temp   = 9'h000;

        case (op)

            // ADD
            // INTENTIONAL BUG:
            // Carry should be temp[8], but is incorrectly forced to 0.
            3'b000: begin
                temp   = {1'b0, a} + {1'b0, b};
                result = temp[7:0];
                carry  = 1'b0;
            end

            // SUB
            3'b001: begin
                temp   = {1'b0, a} - {1'b0, b};
                result = temp[7:0];
                carry  = temp[8];
            end

            // AND
            3'b010: begin
                result = a & b;
            end

            // OR
            3'b011: begin
                result = a | b;
            end

            // XOR
            3'b100: begin
                result = a ^ b;
            end

            // NOT
            3'b101: begin
                result = ~a;
            end

            // SHIFT LEFT
            3'b110: begin
                result = a << 1;
            end

            // SHIFT RIGHT
            3'b111: begin
                result = a >> 1;
            end

            default: begin
                result = 8'h00;
                carry  = 1'b0;
            end

        endcase
    end

    // Result is zero
    assign zero = (result == 8'h00);

endmodule

examples/alu/alu_tb.sv
module alu_tb;

    logic [7:0] a;
    logic [7:0] b;
    logic [2:0] op;

    logic [7:0] result;
    logic       zero;
    logic       carry;

    // Connect testbench to ALU
    alu dut (
        .a      (a),
        .b      (b),
        .op      (op),
        .result (result),
        .zero   (zero),
        .carry  (carry)
    );

    initial begin

        // Waveform generation
        $dumpfile("alu.vcd");
        $dumpvars(0, alu_tb);

        $display("");
        $display("======================================");
        $display("       SILICON SENTINEL ALU TEST");
        $display("======================================");
        $display("");

        // --------------------------------
        // TEST 1: ADD
        // --------------------------------
        a = 8'd10;
        b = 8'd20;
        op = 3'b000;
        #1;

        $display(
            "ADD : %0d + %0d = %0d | carry=%b",
            a, b, result, carry
        );

        // --------------------------------
        // TEST 2: SUB
        // --------------------------------
        a = 8'd30;
        b = 8'd10;
        op = 3'b001;
        #1;

        $display(
            "SUB : %0d - %0d = %0d | carry=%b",
            a, b, result, carry
        );

        // --------------------------------
        // TEST 3: AND
        // --------------------------------
        a = 8'hFF;
        b = 8'h0F;
        op = 3'b010;
        #1;

        $display(
            "AND : %h & %h = %h",
            a, b, result
        );

        // --------------------------------
        // TEST 4: OR
        // --------------------------------
        op = 3'b011;
        #1;

        $display(
            "OR  : %h | %h = %h",
            a, b, result
        );

        // --------------------------------
        // TEST 5: XOR
        // --------------------------------
        op = 3'b100;
        #1;

        $display(
            "XOR : %h ^ %h = %h",
            a, b, result
        );

        // --------------------------------
        // TEST 6: NOT
        // --------------------------------
        a = 8'hAA;
        op = 3'b101;
        #1;

        $display(
            "NOT : ~%h = %h",
            a, result
        );

        // --------------------------------
        // TEST 7: SHIFT LEFT
        // --------------------------------
        a = 8'b00000001;
        op = 3'b110;
        #1;

        $display(
            "SHL : %b -> %b",
            a, result
        );

        // --------------------------------
        // TEST 8: SHIFT RIGHT
        // --------------------------------
        a = 8'b10000000;
        op = 3'b111;
        #1;

        $display(
            "SHR : %b -> %b",
            a, result
        );

        // --------------------------------
        // TEST 9: ZERO FLAG
        // --------------------------------
        a = 8'd10;
        b = 8'd10;
        op = 3'b001;
        #1;

        $display(
            "ZERO: %0d - %0d = %0d | zero=%b",
            a, b, result, zero
        );

        // --------------------------------
        // TEST 10: OVERFLOW / CARRY
        // --------------------------------
        // 255 + 1 = 256
        //
        // 8-bit result should wrap to 0
        // Carry should be 1
        // --------------------------------

        a = 8'hFF;
        b = 8'h01;
        op = 3'b000;
        #1;

        $display("");
        $display("--------------------------------------");
        $display("       FAILURE CAMPAIGN TEST");
        $display("--------------------------------------");

        $display(
            "OVERFLOW: %0d + %0d = %0d | carry=%b",
            a, b, result, carry
        );

        // Check expected behavior
        if (result != 8'h00 || carry != 1'b1) begin

            $display("");
            $display("!!! SILICON SENTINEL FAILURE DETECTED !!!");
            $display("");
            $display("Module      : alu");
            $display("Operation   : ADD");
            $display("Input A     : 0x%h", a);
            $display("Input B     : 0x%h", b);
            $display("");
            $display("EXPECTED");
            $display("Result      : 0x00");
            $display("Carry       : 1");
            $display("");
            $display("ACTUAL");
            $display("Result      : 0x%h", result);
            $display("Carry       : %b", carry);
            $display("");
            $display("Risk        : HIGH");
            $display("Status      : FAILURE");
            $display("");

        end
        else begin

            $display("");
            $display("PASS: Overflow behavior correct.");
            $display("");

        end

        // --------------------------------
        // END
        // --------------------------------

        $display("======================================");
        $display("          TEST COMPLETE");
        $display("======================================");

        $finish;

    end

endmodule

frontend/public/artifacts/1789815774207/waveforms/alu.vcd
$version Generated by VerilatedVcd $end
$timescale 1ps $end
 $scope module $rootio $end
 $upscope $end
 $scope module alu_tb $end
  $var wire 8 # a [7:0] $end
  $var wire 8 $ b [7:0] $end
  $var wire 3 % op [2:0] $end
  $var wire 8 & result [7:0] $end
  $var wire 1 ' zero $end
  $var wire 1 ( carry $end
  $scope module dut $end
   $var wire 8 # a [7:0] $end
   $var wire 8 $ b [7:0] $end
   $var wire 3 % op [2:0] $end
   $var wire 8 & result [7:0] $end
   $var wire 1 ' zero $end
   $var wire 1 ( carry $end
   $var wire 9 ) temp [8:0] $end
  $upscope $end
 $upscope $end
$enddefinitions $end


#0
b00001010 #
b00010100 $
b000 %
b00011110 &
0'
0(
b000011110 )
#1
b00011110 #
b00001010 $
b001 %
b00010100 &
b000010100 )
#2
b11111111 #
b00001111 $
b010 %
b00001111 &
b000000000 )
#3
b011 %
b11111111 &
#4
b100 %
b11110000 &
#5
b10101010 #
b101 %
b01010101 &
#6
b00000001 #
b110 %
b00000010 &
#7
b10000000 #
b111 %
b01000000 &
#8
b00001010 #
b00001010 $
b001 %
b00000000 &
1'
#9
b11111111 #
b00000001 $
b000 %
b100000000 )
